{
    "systemContentOne": "You are a helpful assistant. Your job is to parse job postings and extract key datapoints from each job posting. You will respond as if you are a REST API. Your responses will be well formed JSON objects that can be consumed by other APIs. Each response you provide will always have values in each field. You will think slow to ensure that each response you provide is a well formed JSON Object. \n\n{\n  \"$schema\": \"http://json-schema.org/draft-07/schema#\",\n  \"title\": \"Job Posting\",\n  \"type\": \"object\",\n  \"properties\": {\n    \"job_title\": {\n      \"type\": \"string\",\n      \"description\": \"The title of the job position.\"\n    },\n    \"company\": {\n      \"type\": \"string\",\n      \"description\": \"The name of the company offering the position.\"\n    },\n    \"job_description\": {\n      \"type\": \"string\",\n      \"description\": \"A detailed description of the job role. Written in 4-6 paragraphs. Be verbose\"\n    },\n    \"job_posting_company_information\": {\n      \"type\": \"string\",\n      \"description\": \"Detailed information about the company, its mission, and operations. Written in 4-6 paragraphs. Be verbose.\"\n    },\n    \"job_responsibilities\": {\n      \"type\": \"array\",\n      \"items\": {\n        \"type\": \"string\"\n      },\n      \"description\": \"A list of tasks and responsibilities associated with the job\"\n    },\n    \"job_requirements\": {\n      \"type\": \"array\",\n      \"items\": {\n        \"type\": \"string\"\n      },\n      \"description\": \"A list of requirements candidates must meet for the position. A list of necessary qualifications, experiences, and skills required to perform the job.\"\n    },\n    \"job_skills\": {\n      \"type\": \"array\",\n      \"items\": {\n        \"type\": \"string\"\n      },\n      \"description\": \"A list of specific skills and competencies required for the job.\"\n    },\n    \"is_ai\": {\n      \"type\": \"boolean\",\n      \"description\": \"Indicates if the job involves AI technologies.\"\n    },\n    \"is_genAi\": {\n      \"type\": \"boolean\",\n      \"description\": \"Indicates if the job involves generative AI technologies.\"\n    },\n    \"is_Ai_justification\": {\n      \"type\": \"string\",\n      \"description\": \"Explanation or  justification of the involvement of AI in the job role.\"\n    },\n    \"job_salary\": {\n      \"type\": \"string\",\n      \"pattern\": \"^[0-9,]+ - [0-9,]+$\",\n      \"description\": \"The salary range for the position. Given as a string, like 130,000 - 180,000\"\n    },\n    \"job_keywords\": {\n      \"type\": \"array\",\n      \"items\": {\n        \"type\": \"string\"\n      },\n      \"description\": \"Keywords associated with the job posting.\"\n    },\n    \"salary_low\": {\n      \"type\": \"integer\",\n      \"description\": \"The lower bound of the salary range. Null if salary information is not found\"\n    },\n    \"salary_midpoint\": {\n      \"type\": \"integer\",\n      \"description\": \"The midpoint of the salary range, for benchmarking purposes. Null if salary information is not found\"\n    },\n    \"salary_high\": {\n      \"type\": \"integer\",\n      \"description\": \"The upper bound of the salary range. Null if salary information is not found\"\n    },\n    \"city\": {\n      \"type\": [\"string\", \"null\"],\n      \"description\": \"The city in which the job is located, if applicable. Null if location information is not found\"\n    },\n    \"state\": {\n      \"type\": [\"string\", \"null\"],\n      \"description\": \"The state in which the job is located, if applicable. Null if location information is not found\"\n    },\n    \"work_location_type\": {\n      \"type\": \"string\",\n      \"enum\": [\"Remote\", \"On-site\", \"Hybrid\", null],\n      \"description\": \"The type of work location (e.g., remote, on-site, hybrid). Roles that are hybrid or onsite will often say that in the posting. Otherwise, we assume remote.\"\n    }\n  },\n  \"required\": [\n    \"job_title\",\n    \"company\",\n    \"job_description\",\n    \"job_responsibilities\",\n    \"job_requirements\",\n    \"job_skills\",\n    \"is_ai\",\n    \"is_genAi\",\n    \"job_salary\",\n    \"job_keywords\",\n    \"salary_low\",\n    \"salary_midpoint\",\n    \"salary_high\"\n  ],\n  \"description\": \"A schema for job posting information, detailing the structure and requirements for job listing data.\"\n}",
    
    
    "userContentOne": "\nYou must scan this job posting and provide me information about the following topics. Reminder: you will return a well formed JSON response as a return. \n\n{\n    \"job_title\": String , // The title or designation of the job.\n    \"company\": String, // The name of the company offering the job.\n    \"job_description\": String, // A detailed description of the job role and responsibilities. Written in 4-6 paragraphs. Be verbose\n    \"job_posting_company_information\": String , // Detailed information about the company, its mission, and operations. Written in 4-6 paragraphs. Be verbose\n    \"job_responsibilities\": Collection of Strings [ // A list of tasks and responsibilities associated with the job.\n      \"Manage and assign Adobe licenses and subscriptions to the users.\",\n      \"...\",\n      \"Identify new opportunities and use cases for applying AI/ML to marketing and customer experience challenges.\"\n    ],\n    \"job_requirements\": Collection of Strings [ // A list of necessary qualifications, experiences, and skills required to perform the job.\n      \"Bachelor's degree in marketing, computer science, or related field.\",\n      \"...\",\n      \"Ability to work independently and collaboratively in a fast-paced environment.\"\n    ],\n    \"job_skills\": Collection of Strings[ // A list of specific skills and competencies required for the job.\n      \"Marketing technologies\",\n      \"Adobe Cloud products\",\n      \"...\",\n      \"Communication skills\"\n    ],\n    \"is_ai\": Boolean, // Indicates if the job is related to AI (Artificial Intelligence).\n    \"is_genAi\": Boolean, // Indicates if the job is related to generative AI.\n    \"is_Ai_justification\":  String , // Explanation or justification of how the job is related to AI. We need to have a clear explanation of why is_ai value is set to True or False\n    \"job_salary\": String, // The salary range offered for the job. Given as a string, like 130,000 - 180,000\n    \"job_keywords\": Collection of Strings [ // Keywords related to the job that might be used for search or categorization.\n      \"Lead Product Manager\",\n      \"Adobe Digital Cloud\",\n      \"...\",\n      \"AI/ML Marketing Solutions\"\n    ],\n    \"salary_low\": integer, // The lower end of the salary range. Null if salary information is not found. \n    \"salary_midpoint\": integer, // The midpoint of the salary range. Null if salary information is not found.\n    \"salary_high\": integer, // The higher end of the salary range. Null if salary information is not found.\n    \"city\": String, // The city where the job is located, if applicable. Null if location information is not found.\n    \"state\": String, // The state where the job is located, if applicable. Null if location information is not found.\n    \"work_location_type\": String // The type of work location, e.g., remote, onsite, hybrid. This will always have a value. Roles that are hybrid or onsite will often say that in the posting. Otherwise, we assume remote. \n  }\n  \n\nThese items will be given as a collection:\njob_responsibilities\njob_requirements\njob_skills\njob_keywords\n\nMake sure you complete all of the fields. Make sure you provide a clear justification if a job is an AI (Artificial Intelligence) Job. Please process this information and await further instructions. ",
    
    "assistantContentOne": "\"OK\"",
    
    "userContentTwo": "\"About Lumen\n\nLumen is guided by our belief that humanity is at its best when technology advances the way we live and work. With 450,000 route fiber miles serving customers in more than 60 countries, we deliver the fastest, most secure global platform for applications and data to help businesses, government and communities deliver amazing experiences. Learn more about Lumen’s network, edge cloud, security and communication and collaboration solutions and our purpose to further human progress through technology at news.lumen.com, LinkedIn: /lumentechnologies, Twitter: @lumentechco, Facebook: /lumentechnologies, Instagram: @lumentechnologies and YouTube: /lumentechnologies.\n\nThe Role\n\nThe Lumen marketing operations team is looking for a Lead Product Manager for the Adobe Digital Cloud/Creative Cloud. As the Lead Product Manager this person is responsible for managing and maintaining some pieces within the Adobe stack: licenses and applications for the organization. They will ensure that the users have access to the appropriate tools and services and troubleshoots any issues that may arise. The administrator will also monitor the usage and performance of the Adobe products and provide training and support to the users.\n\nThe Main Responsibilities\n\n\n * Manage and assign Adobe licenses and subscriptions to the users.\n * Provide technical assistance and resolve any issues related to Adobe products and services.\n * Monitor and report on the usage and performance of Adobe products and services.\n * Ensure compliance with Adobe's terms and conditions and security policies.\n * Provide training and guidance to the users on how to use Adobe products and services effectively.\n   \n   \n\nIn addition to the above responsibilities, you will be responsible for leading and delivering innovative solutions that leverage artificial intelligence and machine learning to optimize marketing performance. You will work closely with internal marketing teams to understand their business goals, challenges, and data sources, and design and implement tailored AI/ML solutions that drive measurable results.\n\n\n * Manage the end-to-end delivery of AI/ML marketing solutions, from scoping and planning to deployment and evaluation.\n * Collaborate with data scientists, engineers, and developers to create and deploy scalable and robust AI/ML models and applications.\n * Communicate effectively with stakeholders, translating complex technical concepts into clear and actionable insights and recommendations.\n * Provide thought leadership and best practices on AI/ML marketing solutions, staying abreast of the latest trends and developments in the field.\n * Identify new opportunities and use cases for applying AI/ML to marketing and customer experience challenges.\n   \n   \n\nWhat We Look For In a Candidate\n\n\n * Bachelor's degree in marketing, computer science, or related field.\n * At least 3 years of experience in marketing technologies, preferably with Adobe Cloud products or similar platforms.\n * Strong knowledge of artificial intelligence and machine learning concepts and applications.\n * Knowledge of Adobe Creative Cloud and Digital Cloud administration tools, such as the Admin Console, the Creative Cloud Desktop app, the Creative Cloud Packager, etc.\n * Knowledge of the Salesforce.com chat functionality and the bot capabilities contained within\n * Excellent analytical, troubleshooting, problem-solving, and communication skills.\n * Creative, innovative, and customer-oriented mindset.\n * Ability to work independently and collaboratively in a fast-paced environment.\n   \n   \n\nRequisition #: 331451\n\nWhen applying for a position, you may be subject to a background screen (criminal records check, motor vehicle report, and/or drug screen), depending on the requirements for the position. More information on what’s included in these checks can be found in the Post Offer section of our FAQ page. Job-related concerns noted in the background screen may disqualify you from the new position or your current role. Background results will be evaluated on a case-by-case basis.\n\nEEO Statement\n\nWe are committed to providing equal employment opportunities to all persons regardless of race, color, ancestry, citizenship, national origin, religion, veteran status, disability, genetic characteristic or information, age, gender, sexual orientation, gender identity, marital status, family status, pregnancy, or other legally protected status (collectively, “protected statuses”). We do not tolerate unlawful discrimination in any employment decisions, including recruiting, hiring, compensation, promotion, benefits, discipline, termination, job assignments or training.\n\nNOTE: Pursuant to the San Francisco Fair Chance Ordinance, we will consider for employment qualified applicants with arrest and conviction records.\n\nDisclaimer\n\nThe above job definition information has been designed to indicate the general nature and level of work performed by employees within this classification. It is not designed to contain or be interpreted as a comprehensive inventory of all duties, responsibilities, and qualifications required of employees assigned to this job. Job duties and responsibilities are subject to change based on changing business needs and conditions.\n\nSalary Range\n\nSalary Min\n\n80510\n\nSalary Max\n\n116513\n\nThis information reflects the anticipated base salary range for this position based on current national data. Minimums and maximums may vary based on location. Individual pay is based on skills, experience and other relevant factors.\n\nThis position is eligible for either short-term incentives or sales compensation. Director and VP positions also are eligible for long-term incentive. To learn more about our bonus structure, you can view additional information here. We're able to answer any additional questions you may have as you move through the selection process.\n\nAs part of our comprehensive benefits package, Lumen offers a broad range of Health, Life, Voluntary Lifestyle and other benefits and perks that enhance your physical, mental, emotional and financial wellbeing. You can learn more by clicking here.\n\nNote: For union-represented postings, wage rates and ranges are governed by applicable collective bargaining agreement provisions.\"",
    
    "AssistantContentTwo": "{\n  \"job_title\": \"Lead Product Manager\",\n  \"company\": \"Lumen\",\n  \"job_description\": \"The Lumen marketing operations team is looking for a Lead Product Manager for the Adobe Digital Cloud/Creative Cloud. As the Lead Product Manager this person is responsible for managing and maintaining some pieces within the Adobe stack: licenses and applications for the organization. They will ensure that the users have access to the appropriate tools and services and troubleshoots any issues that may arise. The administrator will also monitor the usage and performance of the Adobe products and provide training and support to the users.\",\n  \"job_posting_company_information\": \"Lumen is guided by our belief that humanity is at its best when technology advances the way we live and work. With 450,000 route fiber miles serving customers in more than 60 countries, we deliver the fastest, most secure global platform for applications and data to help businesses, government and communities deliver amazing experiences. Learn more about Lumen’s network, edge cloud, security and communication and collaboration solutions and our purpose to further human progress through technology at news.lumen.com, LinkedIn: /lumentechnologies, Twitter: @lumentechco, Facebook: /lumentechnologies, Instagram: @lumentechnologies and YouTube: /lumentechnologies.\",\n  \"job_responsibilities\": [\n    \"Manage and assign Adobe licenses and subscriptions to the users.\",\n    \"Provide technical assistance and resolve any issues related to Adobe products and services.\",\n    \"Monitor and report on the usage and performance of Adobe products and services.\",\n    \"Ensure compliance with Adobe's terms and conditions and security policies.\",\n    \"Provide training and guidance to the users on how to use Adobe products and services effectively.\",\n    \"Manage the end-to-end delivery of AI/ML marketing solutions, from scoping and planning to deployment and evaluation.\",\n    \"Collaborate with data scientists, engineers, and developers to create and deploy scalable and robust AI/ML models and applications.\",\n    \"Communicate effectively with stakeholders, translating complex technical concepts into clear and actionable insights and recommendations.\",\n    \"Provide thought leadership and best practices on AI/ML marketing solutions, staying abreast of the latest trends and developments in the field.\",\n    \"Identify new opportunities and use cases for applying AI/ML to marketing and customer experience challenges.\"\n  ],\n  \"job_requirements\": [\n    \"Bachelor's degree in marketing, computer science, or related field.\",\n    \"At least 3 years of experience in marketing technologies, preferably with Adobe Cloud products or similar platforms.\",\n    \"Strong knowledge of artificial intelligence and machine learning concepts and applications.\",\n    \"Knowledge of Adobe Creative Cloud and Digital Cloud administration tools.\",\n    \"Knowledge of Salesforce.com chat functionality and bot capabilities.\",\n    \"Excellent analytical, troubleshooting, problem-solving, and communication skills.\",\n    \"Creative, innovative, and customer-oriented mindset.\",\n    \"Ability to work independently and collaboratively in a fast-paced environment.\"\n  ],\n  \"job_skills\": [\"Marketing technologies\", \"Adobe Cloud products\", \"Artificial intelligence\", \"Machine learning\", \"Analytical skills\", \"Troubleshooting skills\", \"Problem-solving skills\", \"Communication skills\"],\n  \"is_ai\": true,\n  \"is_genAi\": false,\n  \"is_Ai_justification\": \"This job deals with AI as it requires managing and maintaining the Adobe stack, which includes licenses and applications. The role also involves monitoring usage and performance, providing training, and leading and delivering AI/ML marketing solutions.\",\n  \"job_salary\": \"80,510 - 116,513\",\n  \"job_keywords\": [\n    \"Lead Product Manager\",\n    \"Adobe Digital Cloud\",\n    \"Creative Cloud\",\n    \"AI/ML\",\n    \"Marketing\",\n    \"Technical Assistance\",\n    \"Training\",\n    \"Compliance\",\n    \"AI/ML Marketing Solutions\"\n  ],\n  \"salary_low\": 80510,\n  \"salary_midpoint\": 98511,\n  \"salary_high\": 116513,\n  \"city\": null,\n  \"state\": null,\n  \"work_location_type\": \"Remote\"\n}"
    
    }